torchbnn/__init__.py
torchbnn/functional.py
torchbnn/modules/__init__.py
torchbnn/modules/batchnorm.py
torchbnn/modules/conv.py
torchbnn/modules/linear.py
torchbnn/modules/loss.py
torchbnn/modules/module.py
torchbnn/utils/__init__.py
torchbnn/utils/_convert_model.py
torchbnn/utils/freeze_model.py
torchbnn-1.2.dist-info/METADATA
torchbnn-1.2.dist-info/RECORD
torchbnn-1.2.dist-info/WHEEL
torchbnn-1.2.dist-info/top_level.txt
