Metadata-Version: 2.1
Name: torchbnn
Version: 1.2
Summary: Bayesian Neural Network for PyTorch
Home-page: https://github.com/Harry24k/bayesian-neural-network
Author: Harry Kim <24k.harry@gmail.com>
License: MIT
Platform: UNKNOWN
Classifier: Development Status :: 5 - Production/Stable
Classifier: Intended Audience :: Developers
Classifier: Topic :: Scientific/Engineering :: Artificial Intelligence
Classifier: License :: OSI Approved :: MIT License
Classifier: Programming Language :: Python :: 3.6
Classifier: Operating System :: OS Independent
Requires-Python: >=3
